pyutils3/__init__.py
pyutils3/pyutils3.py
py_utils3-1.0.1.dist-info/LICENSE
py_utils3-1.0.1.dist-info/METADATA
py_utils3-1.0.1.dist-info/WHEEL
py_utils3-1.0.1.dist-info/top_level.txt
py_utils3-1.0.1.dist-info/RECORD
