Metadata-Version: 2.1
Name: py-utils3
Version: 1.0.1
Summary: 🔗 Package Guide On https://github.com/mohamedlunar/py-utils3
Home-page: https://github.com/mohamedlunar/py-utils3
Author: MohamedLunar
Author-email: contact.mohamedlunardev@gmail.com
Classifier: Programming Language :: Python :: 3
Classifier: License :: OSI Approved :: MIT License
Classifier: Operating System :: OS Independent
Requires-Python: >=3.10
License-File: LICENSE
Requires-Dist: cryptography
Requires-Dist: requests
